ovos_yes_no_solver/__init__.py
ovos_yes_no_solver/version.py
ovos_yes_no_solver/res/az/yesno.json
ovos_yes_no_solver/res/ca/yesno.json
ovos_yes_no_solver/res/cs/yesno.json
ovos_yes_no_solver/res/da/yesno.json
ovos_yes_no_solver/res/de/yesno.json
ovos_yes_no_solver/res/en/yesno.json
ovos_yes_no_solver/res/es/yesno.json
ovos_yes_no_solver/res/eu/yesno.json
ovos_yes_no_solver/res/fa/yesno.json
ovos_yes_no_solver/res/fr/yesno.json
ovos_yes_no_solver/res/hu/yesno.json
ovos_yes_no_solver/res/it/yesno.json
ovos_yes_no_solver/res/nl/yesno.json
ovos_yes_no_solver/res/pl/yesno.json
ovos_yes_no_solver/res/pt/yesno.json
ovos_yes_no_solver/res/ru/yesno.json
ovos_yes_no_solver/res/sv/yesno.json
ovos_yes_no_solver/res/tr/yesno.json
ovos_yes_no_solver/res/uk/yesno.json
ovos_solver_yes_no_plugin-0.2.8.dist-info/METADATA
ovos_solver_yes_no_plugin-0.2.8.dist-info/WHEEL
ovos_solver_yes_no_plugin-0.2.8.dist-info/entry_points.txt
ovos_solver_yes_no_plugin-0.2.8.dist-info/top_level.txt
ovos_solver_yes_no_plugin-0.2.8.dist-info/zip-safe
ovos_solver_yes_no_plugin-0.2.8.dist-info/RECORD
