Metadata-Version: 2.1
Name: ovos-solver-yes-no-plugin
Version: 0.2.8
Summary: A question solver plugin for OVOS
Home-page: https://github.com/OpenVoiceOS/ovos-solver-YesNo-plugin
Author: jarbasai
Author-email: jarbasai@mailfence.com
License: MIT
Keywords: OVOS openvoiceos plugin utterance fallback query
Platform: UNKNOWN
